neuxml/__init__.py
neuxml/catalog.py
neuxml/schema_data/catalog.xml
neuxml/schema_data/ead.xsd
neuxml/schema_data/eaxs_schema_v1.xsd
neuxml/schema_data/mods-3-4.xsd
neuxml/schema_data/mods.xsd
neuxml/schema_data/oai_dc.xsd
neuxml/schema_data/premis-v2-1.xsd
neuxml/schema_data/premis.xsd
neuxml/schema_data/simpledc20021212.xsd
neuxml/schema_data/tei_all.xsd
neuxml/schema_data/xlink.xsd
neuxml/schema_data/xml.xsd
neuxml/xmlmap/__init__.py
neuxml/xmlmap/cerp.py
neuxml/xmlmap/core.py
neuxml/xmlmap/dc.py
neuxml/xmlmap/eadmap.py
neuxml/xmlmap/fields.py
neuxml/xmlmap/mods.py
neuxml/xmlmap/premis.py
neuxml/xmlmap/teimap.py
neuxml/xpath/__init__.py
neuxml/xpath/ast.py
neuxml/xpath/core.py
neuxml/xpath/lexrules.py
neuxml/xpath/parserules.py
hatch_autorun_neuxml.pth
neuxml-1.0.0.dist-info/METADATA
neuxml-1.0.0.dist-info/WHEEL
neuxml-1.0.0.dist-info/licenses/LICENSE
neuxml-1.0.0.dist-info/RECORD
