Metadata-Version: 2.4
Name: neuxml
Version: 1.0.0
Summary: XPath-based XML data binding
Project-URL: Repository, https://github.com/Princeton-CDH/neuxml
Project-URL: Changelog, https://github.com/Princeton-CDH/neuxml/blob/main/CHANGELOG.rst
Author-email: Center for Digital Humanities at Princeton <cdhdevteam@princeton.edu>
License: Apache-2
License-File: LICENSE
Classifier: Development Status :: 5 - Production/Stable
Classifier: Intended Audience :: Developers
Classifier: License :: OSI Approved :: Apache Software License
Classifier: Natural Language :: English
Classifier: Operating System :: OS Independent
Classifier: Programming Language :: Python
Classifier: Programming Language :: Python :: 3.10
Classifier: Programming Language :: Python :: 3.11
Classifier: Programming Language :: Python :: 3.12
Classifier: Programming Language :: Python :: 3.13
Classifier: Topic :: Software Development :: Libraries :: Python Modules
Classifier: Topic :: Text Processing :: Markup :: XML
Requires-Python: >=3.10
Requires-Dist: lxml>=3.4
Requires-Dist: ply>=3.8
Requires-Dist: rdflib>=3.0
Provides-Extra: dev
Requires-Dist: mock; extra == 'dev'
Requires-Dist: pre-commit; extra == 'dev'
Requires-Dist: pytest-cov; extra == 'dev'
Requires-Dist: pytest-socket; extra == 'dev'
Requires-Dist: pytest>=4.6; extra == 'dev'
Requires-Dist: requests; extra == 'dev'
Requires-Dist: sphinx>=1.3.5; extra == 'dev'
